pybaseball/__init__.py
pybaseball/amateur_draft.py
pybaseball/amateur_draft_by_team.py
pybaseball/batting_leaders.py
pybaseball/fielding_leaders.py
pybaseball/lahman.py
pybaseball/league_batting_stats.py
pybaseball/league_pitching_stats.py
pybaseball/pitching_leaders.py
pybaseball/playerid_lookup.py
pybaseball/plotting.py
pybaseball/retrosheet.py
pybaseball/split_stats.py
pybaseball/standings.py
pybaseball/statcast.py
pybaseball/statcast_batter.py
pybaseball/statcast_fielding.py
pybaseball/statcast_pitcher.py
pybaseball/statcast_pitcher_spin.py
pybaseball/statcast_running.py
pybaseball/team_batting.py
pybaseball/team_fielding.py
pybaseball/team_game_logs.py
pybaseball/team_pitching.py
pybaseball/team_results.py
pybaseball/teamid_lookup.py
pybaseball/top_prospects.py
pybaseball/utils.py
pybaseball/version.py
pybaseball/analysis/__init__.py
pybaseball/analysis/projections/__init__.py
pybaseball/analysis/projections/marcels/__init__.py
pybaseball/analysis/projections/marcels/age_adjustment.py
pybaseball/analysis/projections/marcels/marcels_base.py
pybaseball/analysis/projections/marcels/marcels_batting.py
pybaseball/analysis/projections/marcels/marcels_pitching.py
pybaseball/analysis/trajectories/__init__.py
pybaseball/analysis/trajectories/unit_conversions.py
pybaseball/analysis/trajectories/utils.py
pybaseball/analysis/trajectories/batted_balls/__init__.py
pybaseball/analysis/trajectories/batted_balls/calculator.py
pybaseball/analysis/trajectories/batted_balls/parameters.py
pybaseball/cache/__init__.py
pybaseball/cache/cache.py
pybaseball/cache/cache_config.py
pybaseball/cache/cache_record.py
pybaseball/cache/dataframe_utils.py
pybaseball/cache/file_utils.py
pybaseball/cache/func_utils.py
pybaseball/data/fangraphs_teams.csv
pybaseball/data/mlbstadiums.csv
pybaseball/datahelpers/__init__.py
pybaseball/datahelpers/column_mapper.py
pybaseball/datahelpers/postprocessing.py
pybaseball/datahelpers/singleton.py
pybaseball/datahelpers/statcast_utils.py
pybaseball-2.2.7.dist-info/LICENSE
pybaseball-2.2.7.dist-info/METADATA
pybaseball-2.2.7.dist-info/WHEEL
pybaseball-2.2.7.dist-info/top_level.txt
pybaseball-2.2.7.dist-info/RECORD
