Metadata-Version: 2.1
Name: pybaseball
Version: 2.2.7
Summary: Retrieve baseball data in Python
Home-page: https://github.com/jldbc/pybaseball
Author: James LeDoux
Author-email: ledoux.james.r@gmail.com
Maintainer: Moshe Schorr
License: MIT
Keywords: baseball sabermetrics data statistics statcast web scraping
Classifier: Development Status :: 4 - Beta
Classifier: Intended Audience :: Developers
Classifier: Topic :: Software Development :: Libraries
Classifier: License :: OSI Approved :: MIT License
Classifier: Programming Language :: Python :: 3
Classifier: Programming Language :: Python :: 3.8
Classifier: Programming Language :: Python :: 3.9
Classifier: Programming Language :: Python :: 3.10
Classifier: Programming Language :: Python :: 3.11
Provides-Extra: test
License-File: LICENSE
